yambot/__init__.py
yambot/router.py
yambot/types.py
yambot/yambot.py
yambot_client-0.0.7.dist-info/METADATA
yambot_client-0.0.7.dist-info/WHEEL
yambot_client-0.0.7.dist-info/top_level.txt
yambot_client-0.0.7.dist-info/RECORD
