Metadata-Version: 2.1
Name: yambot_client
Version: 0.0.7
Summary: Unofficial Client for Yandex Messenger Bot API
Home-page: https://github.com/abugrin/yambot
Author: Anton Bugrin
Author-email: abugrin@yandex.ru
Keywords: python yandex.messenger api-client
Classifier: Development Status :: 3 - Alpha
Classifier: Programming Language :: Python :: 3
Classifier: License :: OSI Approved :: MIT License
Classifier: Operating System :: OS Independent
Classifier: Topic :: Software Development :: Libraries :: Python Modules
Requires-Python: >=3.8
Requires-Dist: requests >=2.32.0
